{"cameraMode":{"drawMode":0,"name":"Shaded","section":"Shading Mode"},"sceneLighting":true,"audioPlay":false,"sceneViewState":{"showFog":true,"showMaterialUpdate":false,"showSkybox":true,"showFlares":true,"showImageEffects":true,"showParticleSystems":true},"in2DMode":false,"pivot":{"x":0.6044077277183533,"y":3.7155051231384279,"z":-12.295674324035645},"rotation":{"x":-0.05179109796881676,"y":0.19292157888412476,"z":-0.010197081603109837,"w":-0.9797933101654053},"size":0.1803743839263916,"orthographic":false}